[{"epoch": 355, "start_time": "2022-08-04 06:44", "end_time": "2022-08-09 06:44", "epoch_deleg": 351, "start_time_deleg": "2022-07-15 06:44", "end_time_deleg": "2022-07-20 06:44"}, {"epoch": 354, "start_time": "2022-07-30 06:44", "end_time": "2022-08-04 06:44", "epoch_deleg": 350, "start_time_deleg": "2022-07-10 06:44", "end_time_deleg": "2022-07-15 06:44"}, {"epoch": 353, "start_time": "2022-07-25 06:44", "end_time": "2022-07-30 06:44", "epoch_deleg": 349, "start_time_deleg": "2022-07-05 06:44", "end_time_deleg": "2022-07-10 06:44"}, {"epoch": 352, "start_time": "2022-07-20 06:44", "end_time": "2022-07-25 06:44", "epoch_deleg": 348, "start_time_deleg": "2022-06-30 06:44", "end_time_deleg": "2022-07-05 06:44"}, {"epoch": 351, "start_time": "2022-07-15 06:44", "end_time": "2022-07-20 06:44", "epoch_deleg": 347, "start_time_deleg": "2022-06-25 06:44", "end_time_deleg": "2022-06-30 06:44"}, {"epoch": 350, "start_time": "2022-07-10 06:44", "end_time": "2022-07-15 06:44", "epoch_deleg": 346, "start_time_deleg": "2022-06-20 06:44", "end_time_deleg": "2022-06-25 06:44"}, {"epoch": 349, "start_time": "2022-07-05 06:44", "end_time": "2022-07-10 06:44", "epoch_deleg": 345, "start_time_deleg": "2022-06-15 06:44", "end_time_deleg": "2022-06-20 06:44"}, {"epoch": 348, "start_time": "2022-06-30 06:44", "end_time": "2022-07-05 06:44", "epoch_deleg": 344, "start_time_deleg": "2022-06-10 06:44", "end_time_deleg": "2022-06-15 06:44"}, {"epoch": 347, "start_time": "2022-06-25 06:44", "end_time": "2022-06-30 06:44", "epoch_deleg": 343, "start_time_deleg": "2022-06-05 06:44", "end_time_deleg": "2022-06-10 06:44"}, {"epoch": 346, "start_time": "2022-06-20 06:44", "end_time": "2022-06-25 06:44", "epoch_deleg": 342, "start_time_deleg": "2022-05-31 06:44", "end_time_deleg": "2022-06-05 06:44"}]