[{"epoch": 311, "start_time": "2021-12-27 06:44", "end_time": "2022-01-01 06:44", "epoch_deleg": 307, "start_time_deleg": "2021-12-07 06:44", "end_time_deleg": "2021-12-12 06:44"}, {"epoch": 310, "start_time": "2021-12-22 06:44", "end_time": "2021-12-27 06:44", "epoch_deleg": 306, "start_time_deleg": "2021-12-02 06:44", "end_time_deleg": "2021-12-07 06:44"}, {"epoch": 309, "start_time": "2021-12-17 06:44", "end_time": "2021-12-22 06:44", "epoch_deleg": 305, "start_time_deleg": "2021-11-27 06:44", "end_time_deleg": "2021-12-02 06:44"}, {"epoch": 308, "start_time": "2021-12-12 06:44", "end_time": "2021-12-17 06:44", "epoch_deleg": 304, "start_time_deleg": "2021-11-22 06:44", "end_time_deleg": "2021-11-27 06:44"}, {"epoch": 307, "start_time": "2021-12-07 06:44", "end_time": "2021-12-12 06:44", "epoch_deleg": 303, "start_time_deleg": "2021-11-17 06:44", "end_time_deleg": "2021-11-22 06:44"}, {"epoch": 306, "start_time": "2021-12-02 06:44", "end_time": "2021-12-07 06:44", "epoch_deleg": 302, "start_time_deleg": "2021-11-12 06:44", "end_time_deleg": "2021-11-17 06:44"}, {"epoch": 305, "start_time": "2021-11-27 06:44", "end_time": "2021-12-02 06:44", "epoch_deleg": 301, "start_time_deleg": "2021-11-07 06:44", "end_time_deleg": "2021-11-12 06:44"}, {"epoch": 304, "start_time": "2021-11-22 06:44", "end_time": "2021-11-27 06:44", "epoch_deleg": 300, "start_time_deleg": "2021-11-02 06:44", "end_time_deleg": "2021-11-07 06:44"}, {"epoch": 303, "start_time": "2021-11-17 06:44", "end_time": "2021-11-22 06:44", "epoch_deleg": 299, "start_time_deleg": "2021-10-28 06:44", "end_time_deleg": "2021-11-02 06:44"}, {"epoch": 302, "start_time": "2021-11-12 06:44", "end_time": "2021-11-17 06:44", "epoch_deleg": 298, "start_time_deleg": "2021-10-23 06:44", "end_time_deleg": "2021-10-28 06:44"}]